{"is_source_file": false, "format": "", "description": "", "external_files": [], "external_methods": [], "published": [], "classes": [], "methods": [], "calls": [], "search-terms": ["securechat-messenger-219351-219360", "README.md"], "state": 2, "file_id": 1, "knowledge_revision": 8, "git_revision": "2247414b114121f90979bcff5e931288a4510bd8", "hash": "91c1c65f68df390b14de54cf9c50c84c", "format-version": 4, "code-base-name": "whatsapp_backend", "filename": "README.md", "revision_history": [{"8": "2247414b114121f90979bcff5e931288a4510bd8"}]}